Lab5/lab5mon/project_1/project_1.srcs/sources_1/new/seven_seg_driver.v
`timescale 1ns / 1ps

// ============================================================
//  MODULE: seven_seg_display
//  Purpose: 4-digit 7-segment display with hex output
//  - Multiplexes between 4 digits at ~1 kHz refresh
//  - Converts 4-bit hex nibble to 7-segment cathode pattern
//  - All segments active-LOW (1 = OFF, 0 = ON)
// ============================================================
module seven_seg_display (
    input          clk,
    input          rst,
    input  [15:0]  value,      // 16-bit number to display (4 hex digits)
    output reg [6:0] seg = 7'b1111111,    // Segment outputs (active-LOW)
    output reg [3:0] an  = 4'b1111,       // Anode select (active-LOW)
    output           dp                   // Decimal point (always OFF)
);
    
    assign dp = 1'b1;  // Decimal point always disabled
    
    reg [17:0] div = 0;   // Frequency divider for multiplexing
    reg [1:0]  sel = 0;   // Digit selector (0=rightmost, 3=leftmost)
    reg [3:0]  nib = 0;   // Current 4-bit hex digit being displayed

    // ========================
    // Frequency divider for multiplexing
    // Counts to 262,143 to create ~381 Hz refresh per digit
    // 4 digits × 381 Hz ? 1.5 kHz overall refresh
    // ========================
    always @(posedge clk) begin
        if (rst) begin
            div <= 0; 
            sel <= 0;
        end else begin
            div <= div + 1;
            if (div == 0) sel <= sel + 1;  // Advance digit every 262k clocks
        end
    end

    // ========================
    // Digit/nibble selection logic
    // Selects which 4 bits of value[15:0] to display
    // Also drives anode output (active-LOW: 0=ON, 1=OFF)
    // ========================
    always @(posedge clk) begin
        case (sel)
            2'd0: begin nib <= value[3:0];    an <= 4'b1110; end   // Digit 0 (ones)
            2'd1: begin nib <= value[7:4];    an <= 4'b1101; end   // Digit 1 (sixteens)
            2'd2: begin nib <= value[11:8];   an <= 4'b1011; end   // Digit 2 (256s)
            2'd3: begin nib <= value[15:12];  an <= 4'b0111; end   // Digit 3 (4096s)
        endcase
    end

    // ========================
    // Hex-to-7-segment decoder
    // Converts 4-bit value to segment pattern (active-LOW)
    // Segments: {g,f,e,d,c,b,a}
    //           a=top, b=top-right, c=bottom-right, d=bottom,
    //           e=bottom-left, f=top-left, g=middle
    // ========================
    always @(posedge clk) begin
        if (rst) 
            seg <= 7'b1111111;  // All segments OFF
        else 
            case (nib)
                4'h0: seg <= 7'b1000000;  // 0
                4'h1: seg <= 7'b1111001;  // 1
                4'h2: seg <= 7'b0100100;  // 2
                4'h3: seg <= 7'b0110000;  // 3
                4'h4: seg <= 7'b0011001;  // 4
                4'h5: seg <= 7'b0010010;  // 5
                4'h6: seg <= 7'b0000010;  // 6
                4'h7: seg <= 7'b1111000;  // 7
                4'h8: seg <= 7'b0000000;  // 8
                4'h9: seg <= 7'b0010000;  // 9
                4'hA: seg <= 7'b0001000;  // A
                4'hB: seg <= 7'b0000011;  // B
                4'hC: seg <= 7'b1000110;  // C
                4'hD: seg <= 7'b0100001;  // D
                4'hE: seg <= 7'b0000110;  // E
                4'hF: seg <= 7'b0001110;  // F
                default: seg <= 7'b1111111;
            endcase
    end

endmodule

Lab5/lab5mon/project_1/project_1.srcs/sources_1/new/fsm_counter.v
`timescale 1ns / 1ps
module decrement_counter (
    input clk,
    input rst,                // Global reset
    input rst_btn,            // Mid-count reset
    input load,               // Load enable (from FSM)
    input en,                 // Decrement enable (from FSM)
    input [15:0] sw_val,      // Switch input (bit position = value)
    output reg [15:0] count = 16'h0000,      // Current count value
    output reg count_zero = 1'b1              // Flag: reached zero
);

    always @(posedge clk) begin
        // PRIORITY 1: Reset overrides everything
        if (rst || rst_btn) begin
            count <= 16'h0000;
            count_zero <= 1'b1;
        end 
        // PRIORITY 2: Load takes precedence over decrement
        // Priority encoder: first set bit determines load value
        else if (load) begin
            case (1'b1)
                sw_val[0]:  count <= 4'd0;    // Only bit 0 set ? load 0
                sw_val[1]:  count <= 4'd1;    // Only bit 1 set ? load 1
                sw_val[2]:  count <= 4'd2;    // Only bit 2 set ? load 2
                sw_val[3]:  count <= 4'd3;    // Only bit 3 set ? load 3
                sw_val[4]:  count <= 4'd4;    // Only bit 4 set ? load 4
                sw_val[5]:  count <= 4'd5;    // Only bit 5 set ? load 5
                sw_val[6]:  count <= 4'd6;    // Only bit 6 set ? load 6
                sw_val[7]:  count <= 4'd7;    // Only bit 7 set ? load 7
                sw_val[8]:  count <= 4'd8;    // Only bit 8 set ? load 8
                sw_val[9]:  count <= 4'd9;    // Only bit 9 set ? load 9
                sw_val[10]: count <= 4'd10;   // Only bit 10 set ? load 10
                sw_val[11]: count <= 4'd11;   // Only bit 11 set ? load 11
                sw_val[12]: count <= 4'd12;   // Only bit 12 set ? load 12
                sw_val[13]: count <= 4'd13;   // Only bit 13 set ? load 13
                sw_val[14]: count <= 4'd14;   // Only bit 14 set ? load 14
                sw_val[15]: count <= 4'd15;   // Only bit 15 set (R2) ? load 15
                default:    count <= 16'h0000;
            endcase
            count_zero <= (sw_val == 16'h0000);  // Check if any switch is ON
        end 
        // PRIORITY 3: Decrement when enabled and not already zero
        else if (en && !count_zero) begin
            count <= count - 1'b1;               // Decrement by 1
            count_zero <= (count == 16'h0001);   // Register when next value will be 0
        end
    end

endmodule

Lab5/lab5mon/project_1/project_1.srcs/sources_1/new/fsm.v
`timescale 1ns / 1ps

// ============================================================
//  MODULE: fsm_control
//  Purpose: 3-state Moore FSM controlling countdown process
//  States: IDLE (waiting) -> LOAD (capture switch) -> COUNT (decrement)
// ============================================================
module fsm_control (
    input      clk,
    input      rst,           // Global reset (BTNC)
    input      rst_btn,       // Mid-count reset (BTNU, debounced)
    input      sw_nonzero,    // Trigger: any switch is ON
    input      count_zero,    // Trigger: counter reached zero
    output reg counter_load,  // Signal: load switch value into counter
    output reg counter_en,    // Signal: enable counter decrement
    output reg [1:0] fsm_state = 2'b00
);
    
    // Define state encodings for readability
    localparam [1:0] IDLE=2'b00, LOAD=2'b01, COUNT=2'b10;

    initial begin
        counter_load = 1'b0;
        counter_en   = 1'b0;
    end

    reg [1:0] next_state;

    // ========================
    // Next-state logic (combinational)
    // Determines which state to go to based on current state and inputs
    // ========================
    always @(*) begin
        case (fsm_state)
            // IDLE: Wait for user to set a switch
            IDLE:    next_state = sw_nonzero ? LOAD  : IDLE;
            
            // LOAD: Always transition to COUNT after capturing switch value
            LOAD:    next_state = COUNT;
            
            // COUNT: Stay counting until counter hits zero, then return to IDLE
            COUNT:   next_state = count_zero ? IDLE  : COUNT;
            
            default: next_state = IDLE;
        endcase
    end

    // ========================
    // State register (synchronous)
    // Updates state on every clock edge
    // Both global reset and mid-count reset return to IDLE
    // ========================
    always @(posedge clk) begin
        if (rst || rst_btn) 
            fsm_state <= IDLE;
        else                
            fsm_state <= next_state;
    end

    // ========================
    // Output logic (combinational)
    // Asserts control signals based on NEXT state
    // This ensures signals are ready when state registers update
    // ========================
    always @(*) begin
        counter_load = 1'b0;
        counter_en   = 1'b0;
        if (!(rst || rst_btn)) begin
            case (next_state)
                // In LOAD state: capture the switch value
                LOAD:  counter_load = 1'b1;
                
                // In COUNT state: enable decrement (unless already at zero)
                COUNT: counter_en   = ~count_zero;
                
                default: ;
            endcase
        end
    end

endmodule

Lab5/lab5mon/project_1/project_1.srcs/sources_1/new/switches.v

`timescale 1ns / 1ps

// ============================================================
//  MODULE: switches
//  Purpose: Memory-mapped interface for reading 16 slide switches
//  - Combinational logic (no pipeline delay)
//  - Supports different address modes for flexible SW reading
//  - For this design, hardcoded to return full 16-bit value
// ============================================================
module switches (
    input        clk,
    input        rst,
    input [15:0] btns,
    input [31:0] writeData,
    input        writeEnable,
    input        readEnable,
    input [29:0] memAddress,
    input [15:0] switches,
    output reg [31:0] readData
);

    initial readData = 32'h00000000;

    // ========================
    // Combinational read logic
    // Returns switch value based on address (no delay)
    // ========================
    always @(*) begin
        // On reset: output zero
        if (rst)
            readData = 32'h00000000;
        
        // When read enabled: return data based on address bits [1:0]
        else if (readEnable) begin
            case (memAddress[1:0])
                2'b00: readData = {24'h0, switches[7:0]};    // Lower 8 switches
                2'b01: readData = {24'h0, switches[15:8]};   // Upper 8 switches
                2'b10: readData = {16'h0, switches};         // Full 16-bit value ? USED
                2'b11: readData = {16'h0, btns};             // Button inputs
                default: readData = 32'h0;
            endcase
        end 
        
        // Read disabled: output zero
        else
            readData = 32'h00000000;
    end

endmodule

Lab5/lab5mon/project_1/project_1.srcs/sources_1/new/debouncer.v
`timescale 1ns / 1ps

// ============================================================
//  MODULE: debouncher
//  Purpose: Remove button bounce using 16-bit saturating counter
//  - Counts while button pressed (max 65,535 clocks)
//  - When count[15] rises AND falls (edge detect) ? one-clock pulse
//  - Resets counter immediately when button released
// ============================================================
module debouncher (
    input  clk,
    input  pbin,      // Raw button input (noisy, async)
    output pbout      // Clean debounced pulse output
);
    
    reg [15:0] cnt = 0;   // 16-bit counter (saturates at bit 15)
    reg        q0  = 0;   // First FF for edge detection
    reg        q1  = 0;   // Second FF for edge detection

    always @(posedge clk) begin
        // When button released: reset counter
        if (!pbin)           
            cnt <= 0;
        
        // When button held: count up until bit 15 saturates
        else if (!cnt[15])   
            cnt <= cnt + 1;
        
        // Shift registers for edge detection (rising edge of cnt[15])
        q0 <= cnt[15];
        q1 <= q0;
    end
    
    // Output pulse: detect rising edge of cnt[15]
    // pbout = 1 for ONE clock when q0 goes from 0?1
    assign pbout = q0 & ~q1;

endmodule

Lab5/lab5mon/project_1/project_1.srcs/sources_1/new/top.v
`timescale 1ns / 1ps

// ============================================================
//  MODULE: lab5_top
//  Purpose: Top-level integration of all 5 modules
//  Signal flow:
//    SW[15:0] ? switches ? FSM & counter
//    BTNC ? debouncer ? FSM & counter
//    FSM ? counter (load, en signals)
//    Counter ? 7-seg display
// ============================================================
module lab5_top (
    input        clk,           // 100 MHz oscillator (W5)
    input        rst,           // Global reset button BTNC (U18)
    input        rst_btn_raw,   // Debounce-input reset button BTNU (T18)
    input [15:0] sw,            // Physical slide switches (SW[15:0])
    output [6:0] seg,           // 7-segment cathodes active-LOW (W7-U7)
    output [3:0] an,            // 7-segment anodes active-LOW (U2-W4)
    output       dp             // Decimal point (always OFF, V7)
);

    // ========================
    // Internal wires
    // ========================
    wire        rst_btn;        // Debounced reset pulse from BTNU
    wire [31:0] sw_read_data;   // 32-bit output from switches module
    wire [15:0] sw_val;         // Extracted 16-bit switch value
    wire        sw_nonzero;     // Flag: any switch is ON
    wire        counter_load;   // FSM output: load counter now
    wire        counter_en;     // FSM output: enable decrement now
    wire [15:0] count;          // Counter value to display
    wire        count_zero;     // Counter flag: reached zero

    // ----------------------------------------------------------
    // INSTANCE 1: Debouncher
    // Cleans up BTNU input and produces one-clock pulse
    // ----------------------------------------------------------
    debouncher u_debounce (
        .clk   (clk),
        .pbin  (rst_btn_raw),
        .pbout (rst_btn)
    );

    // ----------------------------------------------------------
    // INSTANCE 2: Switches interface
    // Reads all 16 slide switches via memory-mapped interface
    // memAddress = {28'h0, 2'b10} selects full 16-bit mode
    // ----------------------------------------------------------
    switches u_switches (
        .clk        (clk),
        .rst        (rst),
        .btns       (16'h0000),
        .writeData  (32'h00000000),
        .writeEnable(1'b0),
        .readEnable (1'b1),
        .memAddress ({28'h0, 2'b10}),  // Address mode 2 = full 16-bit read
        .switches   (sw),
        .readData   (sw_read_data)
    );

    // Extract 16-bit value and detect if any switch is ON
    assign sw_val     = sw_read_data[15:0];
    assign sw_nonzero = (sw_val != 16'h0000);

    // ----------------------------------------------------------
    // INSTANCE 3: FSM Controller
    // 3-state machine managing countdown sequence
    // ----------------------------------------------------------
    fsm_control u_fsm (
        .clk         (clk),
        .rst         (rst),
        .rst_btn     (rst_btn),
        .sw_nonzero  (sw_nonzero),
        .count_zero  (count_zero),
        .counter_load(counter_load),
        .counter_en  (counter_en)
    );

    // ----------------------------------------------------------
    // INSTANCE 4: Decrement Counter with Priority Encoder
    // Loads switch BIT POSITION (0-15) as countdown value
    // Example: SW[15] (R2) only ? load 15
    //          SW[7] only ? load 7
    //          SW[0] only ? load 0
    // ----------------------------------------------------------
    decrement_counter u_counter (
        .clk       (clk),
        .rst       (rst),
        .rst_btn   (rst_btn),
        .load      (counter_load),
        .en        (counter_en),
        .sw_val    (sw_val),
        .count     (count),
        .count_zero(count_zero)
    );

    // ----------------------------------------------------------
    // INSTANCE 5: Seven-Segment Display
    // Multiplexes 4 digits and converts count to hex display
    // ----------------------------------------------------------
    seven_seg_display u_7seg (
        .clk  (clk),
        .rst  (rst),
        .value(count),
        .seg  (seg),
        .an   (an),
        .dp   (dp)
    );

endmodule

Lab5/lab5mon/project_1/project_1.srcs/sources_1/new/testbench.v
`timescale 1ns / 1ps

// ============================================================
//  Simple Testbench - Lab 5 FSM with Priority Encoder
//  Tests: reset, idle, countdown (bit position = value)
// ============================================================
module tb_fsm;
    reg        clk         = 0;
    reg        rst         = 0;
    reg        rst_btn_raw = 0;
    reg [15:0] sw          = 0;
    wire [6:0] seg;
    wire [3:0] an;
    wire       dp;
    
    always #5 clk = ~clk;   // 100 MHz
    
    // Instantiate top module
    lab5_top uut (
        .clk        (clk),
        .rst        (rst),
        .rst_btn_raw(rst_btn_raw),
        .sw         (sw),
        .seg        (seg),
        .an         (an),
        .dp         (dp)
    );
    
    // Internal probes
    wire [1:0]  state = uut.u_fsm.fsm_state;
    wire [15:0] count = uut.u_counter.count;
    wire        load  = uut.u_fsm.counter_load;
    wire        en    = uut.u_fsm.counter_en;
    
    initial begin
        $dumpfile("tb_fsm.vcd");
        $dumpvars(0, tb_fsm);
    end
    
    // Print every clock edge
    initial begin
        $display("  Time | state | count | load | en");
        $display("  -----|-------|-------|------|----");
        forever begin
            @(posedge clk); #1;
            $display("  %0t  |  %2b   | %04h  |  %b   |  %b",
                     $time, state, count, load, en);
        end
    end
    
    initial begin
        $display("=== Lab 5 FSM Testbench (Priority Encoder) ===\n");
        
        // -------------------------------------------------
        // TEST 1: Global reset -> state=IDLE, count=0
        // -------------------------------------------------
        $display("[TEST 1] Global reset");
        rst = 1;
        repeat(4) @(posedge clk); #1;
        rst = 0;
        @(posedge clk); #1;
        $display("  >> state=%b  count=%04h  (expect: state=00, count=0000)\n",
                 state, count);
        
        // -------------------------------------------------
        // TEST 2: sw=0 -> FSM stays in IDLE
        // -------------------------------------------------
        $display("[TEST 2] sw=0 stays IDLE");
        sw = 16'h0000;
        repeat(4) @(posedge clk); #1;
        $display("  >> state=%b  count=%04h  (expect: state=00, count=0000)\n",
                 state, count);
        
        // -------------------------------------------------
        // TEST 3: SW[5] only (bit 5 = load value 5)
        //         FSM should: IDLE->LOAD->COUNT 5,4,3,2,1,0 -> IDLE
        //         PRIORITY ENCODER: only bit 5 set ? loads 5
        // -------------------------------------------------
        $display("[TEST 3] SW[5] only (bit position 5 = value 5)");
        $display("         Setting sw = 16'h0020 (only bit 5)");
        sw = 16'h0020;           // Only bit 5 set ? priority encoder loads 5
        @(posedge clk);          // FSM sees sw!=0, goes to LOAD, counter loads 5
        sw = 16'h0000;           // clear sw immediately so it won't reload
        repeat(10) @(posedge clk); #1;  // wait for 5 decrements + return to IDLE
        $display("  >> state=%b  count=%04h  (expect: state=00, count=0000)\n",
                 state, count);
        
        // -------------------------------------------------
        // TEST 4: SW[8] only (bit 8 = load value 8), then reset button mid-count
        //         FSM should jump back to IDLE immediately
        // -------------------------------------------------
        $display("[TEST 4] SW[8] only (bit 8 = value 8), reset button mid-count");
        $display("         Setting sw = 16'h0100 (only bit 8)");
        sw = 16'h0100;           // Only bit 8 set ? priority encoder loads 8
        @(posedge clk);          // LOAD: counter loads 8
        sw = 16'h0000;           // clear sw
        repeat(3) @(posedge clk); #1; // let it count down 3 steps (count should be 5)
        $display("  >> mid-count: state=%b  count=%04h  (expect: state=10, count should be 5ish)",
                 state, count);
        
        // Hold button 30 cycles to satisfy debouncer
        rst_btn_raw = 1;
        repeat(30) @(posedge clk);
        rst_btn_raw = 0;
        @(posedge clk); #1;
        $display("  >> after btn: state=%b  count=%04h  (expect: state=00, count=0000)\n",
                 state, count);
        
        // -------------------------------------------------
        // TEST 5: SW[15] (R2) only ? load value 15 (0x000F)
        // -------------------------------------------------
        $display("[TEST 5] SW[15] only (R2 = bit 15 = value 15)");
        $display("         Setting sw = 16'h8000 (only bit 15)");
        sw = 16'h8000;           // Only bit 15 set ? priority encoder loads 15
        repeat(5) @(posedge clk);
        $display("  >> state=%b  count=%04h  (expect: state=10, count=000F)\n",
                 state, count);
        
        sw = 16'h0000;
        repeat(5) @(posedge clk);
        
        // -------------------------------------------------
        // TEST 6: SW[0] only ? load value 0 (0x0000)
        // -------------------------------------------------
        $display("[TEST 6] SW[0] only (bit 0 = value 0)");
        $display("         Setting sw = 16'h0001 (only bit 0)");
        sw = 16'h0001;           // Only bit 0 set ? priority encoder loads 0
        repeat(5) @(posedge clk);
        $display("  >> state=%b  count=%04h  (expect: state=10, count=0000)\n",
                 state, count);
        
        sw = 16'h0000;
        repeat(5) @(posedge clk);
        
        // -------------------------------------------------
        // TEST 7: Multiple bits set (SW[3] and SW[7])
        //         Priority encoder picks lowest bit ? bit 3 = value 3
        // -------------------------------------------------
        $display("[TEST 7] SW[3] and SW[7] both set");
        $display("         Setting sw = 16'h0088 (bits 3 and 7)");
        $display("         Priority encoder picks bit 3 ? loads value 3");
        sw = 16'h0088;           // Bits 3 and 7 set ? picks bit 3, loads 3
        repeat(5) @(posedge clk);
        $display("  >> state=%b  count=%04h  (expect: state=10, count=0003)\n",
                 state, count);
        
        sw = 16'h0000;
        repeat(4) @(posedge clk);
        
        $display("=== Testbench done ===");
        $finish;
    end

endmodule

Lab5/lab5mon/project_1/project_1.sim/sim_1/behav/xsim/tb_fsm.vcd
$date
   Tue Feb 17 16:14:56 2026
$end
$version
  2020.1
$end
$timescale
  1ps
$end
$scope module tb_fsm $end
$var reg 1 ! clk $end
$var reg 1 " rst $end
$var reg 1 # rst_btn_raw $end
$var reg 16 $ sw [15:0] $end
$var wire 7 % seg [6:0] $end
$var wire 4 & an [3:0] $end
$var wire 1 ' dp $end
$var wire 2 ( state [1:0] $end
$var wire 16 ) count [15:0] $end
$var wire 1 * load $end
$var wire 1 + en $end
$scope module uut $end
$var wire 1 , clk $end
$var wire 1 - rst $end
$var wire 1 . rst_btn_raw $end
$var wire 16 / sw [15:0] $end
$var wire 7 % seg [6:0] $end
$var wire 4 & an [3:0] $end
$var wire 1 ' dp $end
$var wire 1 0 rst_btn $end
$var wire 32 1 sw_read_data [31:0] $end
$var wire 16 2 sw_val [15:0] $end
$var wire 1 3 sw_nonzero $end
$var wire 1 4 counter_load $end
$var wire 1 5 counter_en $end
$var wire 16 6 count [15:0] $end
$var wire 1 7 count_zero $end
$scope module u_debounce $end
$var wire 1 , clk $end
$var wire 1 . pbin $end
$var wire 1 0 pbout $end
$var reg 16 8 cnt [15:0] $end
$var reg 1 9 q0 $end
$var reg 1 : q1 $end
$upscope $end
$scope module u_switches $end
$var wire 1 , clk $end
$var wire 1 - rst $end
$var wire 16 ; btns [15:0] $end
$var wire 32 < writeData [31:0] $end
$var wire 1 = writeEnable $end
$var wire 1 > readEnable $end
$var wire 30 ? memAddress [29:0] $end
$var wire 16 / switches [15:0] $end
$var reg 32 @ readData [31:0] $end
$upscope $end
$scope module u_fsm $end
$var wire 1 , clk $end
$var wire 1 - rst $end
$var wire 1 0 rst_btn $end
$var wire 1 3 sw_nonzero $end
$var wire 1 7 count_zero $end
$var reg 1 A counter_load $end
$var reg 1 B counter_en $end
$var reg 2 C fsm_state [1:0] $end
$var reg 2 D next_state [1:0] $end
$var parameter 2 E IDLE [1:0] $end
$var parameter 2 F LOAD [1:0] $end
$var parameter 2 G COUNT [1:0] $end
$upscope $end
$scope module u_counter $end
$var wire 1 , clk $end
$var wire 1 - rst $end
$var wire 1 0 rst_btn $end
$var wire 1 4 load $end
$var wire 1 5 en $end
$var wire 16 2 sw_val [15:0] $end
$var reg 16 H count [15:0] $end
$var reg 1 I count_zero $end
$upscope $end
$scope module u_7seg $end
$var wire 1 , clk $end
$var wire 1 - rst $end
$var wire 16 6 value [15:0] $end
$var reg 7 J seg [6:0] $end
$var reg 4 K an [3:0] $end
$var wire 1 ' dp $end
$var reg 18 L div [17:0] $end
$var reg 2 M sel [1:0] $end
$var reg 4 N nib [3:0] $end
$upscope $end
$upscope $end
$upscope $end
$enddefinitions $end
#0
$dumpvars
0!
1"
0#
b0 $
b1111111 %
b1111 &
1'
b0 (
b0 )
0*
0+
0,
1-
0.
b0 /
00
b0 1
b0 2
03
04
05
b0 6
17
b0 8
09
0:
b0 ;
b0 <
0=
1>
b10 ?
b0 @
0A
0B
b0 C
b0 D
b0 E
b1 F
b10 G
b0 H
1I
b1111111 J
b1111 K
b0 L
b0 M
b0 N
$end
#5000
1!
b1110 &
1,
09
0:
b0 C
b0 H
1I
b1111111 J
b1110 K
#10000
0!
0,
#15000
1!
1,
09
0:
b0 C
b0 H
1I
b1111111 J
b1110 K
#20000
0!
0,
#25000
1!
1,
09
0:
b0 C
b0 H
1I
b1111111 J
b1110 K
#30000
0!
0,
#35000
1!
1,
09
0:
b0 C
b0 H
1I
b1111111 J
b1110 K
#36000
0"
0-
b0 @
0A
0B
#40000
0!
0,
#45000
1!
b1000000 %
1,
09
0:
b0 C
b1000000 J
b1110 K
b1 L
b1 M
#46000
b0 $
#50000
0!
0,
#55000
1!
b1101 &
1,
09
0:
b0 C
b1000000 J
b1101 K
b10 L
#60000
0!
0,
#65000
1!
1,
09
0:
b0 C
b1000000 J
b1101 K
b11 L
#70000
0!
0,
#75000
1!
1,
09
0:
b0 C
b1000000 J
b1101 K
b100 L
#80000
0!
0,
#85000
1!
1,
09
0:
b0 C
b1000000 J
b1101 K
b101 L
#86000
b100000 $
1*
b100000 /
b100000 1
b100000 2
13
14
b100000 @
1A
0B
b1 D
#90000
0!
0,
#95000
1!
b0 $
b1 (
b101 )
0*
1+
1,
b0 /
b0 1
b0 2
03
04
15
b101 6
07
09
0:
b0 @
0A
1B
b1 C
b10 D
b101 H
0I
b1000000 J
b1101 K
b110 L
#100000
0!
0,
#105000
1!
b10 (
b100 )
1,
b100 6
09
0:
b10 C
b10 D
b100 H
0I
b1000000 J
b1101 K
b111 L
#110000
0!
0,
#115000
1!
b11 )
1,
b11 6
09
0:
b10 C
b11 H
0I
b1000000 J
b1101 K
b1000 L
#120000
0!
0,
#125000
1!
b10 )
1,
b10 6
09
0:
b10 C
b10 H
0I
b1000000 J
b1101 K
b1001 L
#130000
0!
0,
#135000
1!
b1 )
1,
b1 6
09
0:
b10 C
b1 H
0I
b1000000 J
b1101 K
b1010 L
#140000
0!
0,
#145000
1!
b0 )
0+
1,
05
b0 6
17
09
0:
0A
0B
b10 C
b0 D
b0 H
1I
b1000000 J
b1101 K
b1011 L
#150000
0!
0,
#155000
1!
b0 (
1,
09
0:
b0 C
b0 D
b1000000 J
b1101 K
b1100 L
#160000
0!
0,
#165000
1!
1,
09
0:
b0 C
b1000000 J
b1101 K
b1101 L
#170000
0!
0,
#175000
1!
1,
09
0:
b0 C
b1000000 J
b1101 K
b1110 L
#180000
0!
0,
#185000
1!
1,
09
0:
b0 C
b1000000 J
b1101 K
b1111 L
#190000
0!
0,
#195000
1!
1,
09
0:
b0 C
b1000000 J
b1101 K
b10000 L
#196000
b100000000 $
1*
b100000000 /
b100000000 1
b100000000 2
13
14
b100000000 @
1A
0B
b1 D
#200000
0!
0,
#205000
1!
b0 $
b1 (
b1000 )
0*
1+
1,
b0 /
b0 1
b0 2
03
04
15
b1000 6
07
09
0:
b0 @
0A
1B
b1 C
b10 D
b1000 H
0I
b1000000 J
b1101 K
b10001 L
#210000
0!
0,
#215000
1!
b10 (
b111 )
1,
b111 6
09
0:
b10 C
b10 D
b111 H
0I
b1000000 J
b1101 K
b10010 L
#220000
0!
0,
#225000
1!
b110 )
1,
b110 6
09
0:
b10 C
b110 H
0I
b1000000 J
b1101 K
b10011 L
#230000
0!
0,
#235000
1!
b101 )
1,
b101 6
09
0:
b10 C
b101 H
0I
b1000000 J
b1101 K
b10100 L
#236000
1#
1.
#240000
0!
0,
#245000
1!
b100 )
1,
b100 6
b1 8
09
0:
b10 C
b100 H
0I
b1000000 J
b1101 K
b10101 L
#250000
0!
0,
#255000
1!
b11 )
1,
b11 6
b10 8
09
0:
b10 C
b11 H
0I
b1000000 J
b1101 K
b10110 L
#260000
0!
0,
#265000
1!
b10 )
1,
b10 6
b11 8
09
0:
b10 C
b10 H
0I
b1000000 J
b1101 K
b10111 L
#270000
0!
0,
#275000
1!
b1 )
1,
b1 6
b100 8
09
0:
b10 C
b1 H
0I
b1000000 J
b1101 K
b11000 L
#280000
0!
0,
#285000
1!
b0 )
0+
1,
05
b0 6
17
b101 8
09
0:
0A
0B
b10 C
b0 D
b0 H
1I
b1000000 J
b1101 K
b11001 L
#290000
0!
0,
#295000
1!
b0 (
1,
b110 8
09
0:
b0 C
b0 D
b1000000 J
b1101 K
b11010 L
#300000
0!
0,
#305000
1!
1,
b111 8
09
0:
b0 C
b1000000 J
b1101 K
b11011 L
#310000
0!
0,
#315000
1!
1,
b1000 8
09
0:
b0 C
b1000000 J
b1101 K
b11100 L
#320000
0!
0,
#325000
1!
1,
b1001 8
09
0:
b0 C
b1000000 J
b1101 K
b11101 L
#330000
0!
0,
#335000
1!
1,
b1010 8
09
0:
b0 C
b1000000 J
b1101 K
b11110 L
#340000
0!
0,
#345000
1!
1,
b1011 8
09
0:
b0 C
b1000000 J
b1101 K
b11111 L
#350000
0!
0,
#355000
1!
1,
b1100 8
09
0:
b0 C
b1000000 J
b1101 K
b100000 L
#360000
0!
0,
#365000
1!
1,
b1101 8
09
0:
b0 C
b1000000 J
b1101 K
b100001 L
#370000
0!
0,
#375000
1!
1,
b1110 8
09
0:
b0 C
b1000000 J
b1101 K
b100010 L
#380000
0!
0,
#385000
1!
1,
b1111 8
09
0:
b0 C
b1000000 J
b1101 K
b100011 L
#390000
0!
0,
#395000
1!
1,
b10000 8
09
0:
b0 C
b1000000 J
b1101 K
b100100 L
#400000
0!
0,
#405000
1!
1,
b10001 8
09
0:
b0 C
b1000000 J
b1101 K
b100101 L
#410000
0!
0,
#415000
1!
1,
b10010 8
09
0:
b0 C
b1000000 J
b1101 K
b100110 L
#420000
0!
0,
#425000
1!
1,
b10011 8
09
0:
b0 C
b1000000 J
b1101 K
b100111 L
#430000
0!
0,
#435000
1!
1,
b10100 8
09
0:
b0 C
b1000000 J
b1101 K
b101000 L
#440000
0!
0,
#445000
1!
1,
b10101 8
09
0:
b0 C
b1000000 J
b1101 K
b101001 L
#450000
0!
0,
#455000
1!
1,
b10110 8
09
0:
b0 C
b1000000 J
b1101 K
b101010 L
#460000
0!
0,
#465000
1!
1,
b10111 8
09
0:
b0 C
b1000000 J
b1101 K
b101011 L
#470000
0!
0,
#475000
1!
1,
b11000 8
09
0:
b0 C
b1000000 J
b1101 K
b101100 L
#480000
0!
0,
#485000
1!
1,
b11001 8
09
0:
b0 C
b1000000 J
b1101 K
b101101 L
#490000
0!
0,
#495000
1!
1,
b11010 8
09
0:
b0 C
b1000000 J
b1101 K
b101110 L
#500000
0!
0,
#505000
1!
1,
b11011 8
09
0:
b0 C
b1000000 J
b1101 K
b101111 L
#510000
0!
0,
#515000
1!
1,
b11100 8
09
0:
b0 C
b1000000 J
b1101 K
b110000 L
#520000
0!
0,
#525000
1!
1,
b11101 8
09
0:
b0 C
b1000000 J
b1101 K
b110001 L
#530000
0!
0,
#535000
1!
0#
1,
0.
b0 8
09
0:
b0 C
b1000000 J
b1101 K
b110010 L
#540000
0!
0,
#545000
1!
1,
09
0:
b0 C
b1000000 J
b1101 K
b110011 L
#546000
b1000000000000000 $
1*
b1000000000000000 /
b1000000000000000 1
b1000000000000000 2
13
14
b1000000000000000 @
1A
0B
b1 D
#550000
0!
0,
#555000
1!
b1 (
b1111 )
0*
1+
1,
04
15
b1111 6
07
09
0:
0A
1B
b1 C
b10 D
b1111 H
0I
b1000000 J
b1101 K
b110100 L
#560000
0!
0,
#565000
1!
b10 (
b1110 )
1,
b1110 6
09
0:
b10 C
b10 D
b1110 H
0I
b1000000 J
b1101 K
b110101 L
#570000
0!
0,
#575000
1!
b1101 )
1,
b1101 6
09
0:
b10 C
b1101 H
0I
b1000000 J
b1101 K
b110110 L
#580000
0!
0,
#585000
1!
b1100 )
1,
b1100 6
09
0:
b10 C
b1100 H
0I
b1000000 J
b1101 K
b110111 L
#590000
0!
0,
#595000
1!
b0 $
b1011 )
1,
b0 /
b0 1
b0 2
03
b1011 6
09
0:
b0 @
b10 C
b10 D
b1011 H
0I
b1000000 J
b1101 K
b111000 L
#600000
0!
0,
#605000
1!
b1010 )
1,
b1010 6
09
0:
b10 C
b1010 H
0I
b1000000 J
b1101 K
b111001 L
#610000
0!
0,
#615000
1!
b1001 )
1,
b1001 6
09
0:
b10 C
b1001 H
0I
b1000000 J
b1101 K
b111010 L
#620000
0!
0,
#625000
1!
b1000 )
1,
b1000 6
09
0:
b10 C
b1000 H
0I
b1000000 J
b1101 K
b111011 L
#630000
0!
0,
#635000
1!
b111 )
1,
b111 6
09
0:
b10 C
b111 H
0I
b1000000 J
b1101 K
b111100 L
#640000
0!
0,
#645000
1!
b1 $
b110 )
1,
b1 /
b1 1
b1 2
13
b110 6
09
0:
b1 @
b10 C
b10 D
b110 H
0I
b1000000 J
b1101 K
b111101 L
#650000
0!
0,
#655000
1!
b101 )
1,
b101 6
09
0:
b10 C
b101 H
0I
b1000000 J
b1101 K
b111110 L
#660000
0!
0,
#665000
1!
b100 )
1,
b100 6
09
0:
b10 C
b100 H
0I
b1000000 J
b1101 K
b111111 L
#670000
0!
0,
#675000
1!
b11 )
1,
b11 6
09
0:
b10 C
b11 H
0I
b1000000 J
b1101 K
b1000000 L
#680000
0!
0,
