Lab7/lab7_friday/lab7/lab7.srcs/sources_1/new/RegisterFile.v
`timescale 1ns / 1ps

module RegisterFile (
    input clk,
    input rst,
    input WriteEnable,
    input [4:0] rs1,
    input [4:0] rs2,
    input [4:0] rd,
    input [31:0] WriteData,
    output reg [31:0] ReadData1,
    output reg [31:0] ReadData2
);

    reg [31:0] regs [31:0];
    integer i;

    //Synchronous write and reset
    always @(posedge clk) begin
        //Clear all registers on reset
        if (rst) begin
            for (i = 0; i < 32; i = i + 1)
                regs[i] <= 32'b0;
        end else begin
            //Write only if enabled and destination is not x0
            if (WriteEnable && (rd != 5'b0))
                regs[rd] <= WriteData;
        end
    end

    //Asynchronous reads
    reg [31:0] ReadData1, ReadData2;

    always @(*) begin
        if (rs1 == 5'b0)
            ReadData1 = 32'b0;
        else
            ReadData1 = regs[rs1];
    end

    always @(*) begin
        if(rs2==5'b0)
            ReadData2=32'b0;
        else
            ReadData2=regs[rs2];
    end

endmodule

Lab7/lab7_friday/lab7/lab7.srcs/sim_1/new/RegisterFile_tb.v
`timescale 1ns / 1ps

module RegisterFile_tb;

    // DUT Inputs
    reg clk;
    reg rst;
    reg WriteEnable;
    reg [4:0]  rs1, rs2, rd;
    reg [31:0] WriteData;

    //DUT Outputs
    wire [31:0] ReadData1, ReadData2;

    //Instantiate DUT
    RegisterFile uut (
        .clk(clk), .rst(rst),
        .WriteEnable(WriteEnable),
        .rs1(rs1), .rs2(rs2), .rd(rd),
        .WriteData(WriteData),
        .ReadData1(ReadData1),
        .ReadData2(ReadData2)
    );

    //10 ns clock period
    initial clk = 0;
    always #5 clk = ~clk;

    //apply a write, then check reads on next cycle
    task write_reg;
        input [4:0]  addr;
        input [31:0] data;
        begin
            rd = addr; WriteData = data; WriteEnable = 1;
            @(posedge clk); #1;
            WriteEnable = 0;
        end
    endtask

    //TEST CASES
    
    integer pass_count;
    integer fail_count;

    task check;
        input [31:0] got;
        input [31:0] expected;
        input [63:0] test_num;
        begin
            if (got === expected) begin
                $display("PASS [Test %0d]: got 0x%08h", test_num, got);
                pass_count = pass_count + 1;
            end else begin
                $display("FAIL [Test %0d]: expected 0x%08h, got 0x%08h",
                         test_num, expected, got);
                fail_count = fail_count + 1;
            end
        end
    endtask

    initial begin
        pass_count = 0; fail_count = 0;

        // Initialise inputs
        rst = 1; WriteEnable = 0;
        rs1 = 0; rs2 = 0; rd = 0; WriteData = 0;
        @(posedge clk); #1;
        rst = 0;

        write_reg(5'd5, 32'hDEADBEEF);
        rs1 = 5'd5;
        #1;
        check(ReadData1, 32'hDEADBEEF, 1);

        write_reg(5'd0, 32'hFFFFFFFF);
        rs1 = 5'd0;
        #1;
        check(ReadData1, 32'h00000000, 2);

        write_reg(5'd7, 32'hA5A5A5A5);
        rs1 = 5'd5; rs2 = 5'd7;
        #1;
        check(ReadData1, 32'hDEADBEEF, 3);
        check(ReadData2, 32'hA5A5A5A5, 3);

        write_reg(5'd5, 32'h12345678);
        rs1 = 5'd5;
        #1;
        check(ReadData1, 32'h12345678, 4);
        
        rst = 1;
        @(posedge clk); #1;
        rst = 0;
        rs1 = 5'd5; rs2 = 5'd7;
        #1;
        check(ReadData1, 32'h00000000, 5);
        check(ReadData2, 32'h00000000, 5);

        // Summary
        $display("------------------------------");
        $display("Results: %0d PASSED, %0d FAILED", pass_count, fail_count);
        $display("------------------------------");
        $finish;
    end

    // Dump waveforms
    initial begin
        $dumpfile("RegisterFile_tb.vcd");
        $dumpvars(0, RegisterFile_tb);
    end

endmodule

Lab7/lab7_friday/lab7/lab7.sim/sim_1/behav/xsim/RegisterFile_tb.vcd
$date
   Fri Mar  6 22:32:36 2026
$end
$version
  2020.1
$end
$timescale
  1ps
$end
$scope module RegisterFile_tb $end
$var reg 1 ! clk $end
$var reg 1 " rst $end
$var reg 1 # WriteEnable $end
$var reg 5 $ rs1 [4:0] $end
$var reg 5 % rs2 [4:0] $end
$var reg 5 & rd [4:0] $end
$var reg 32 ' WriteData [31:0] $end
$var wire 32 ( ReadData1 [31:0] $end
$var wire 32 ) ReadData2 [31:0] $end
$var integer 32 * pass_count $end
$var integer 32 + fail_count $end
$scope module uut $end
$var wire 1 , clk $end
$var wire 1 - rst $end
$var wire 1 . WriteEnable $end
$var wire 5 / rs1 [4:0] $end
$var wire 5 0 rs2 [4:0] $end
$var wire 5 1 rd [4:0] $end
$var wire 32 2 WriteData [31:0] $end
$var reg 32 3 ReadData1 [31:0] $end
$var reg 32 4 ReadData2 [31:0] $end
$var integer 32 5 i $end
$upscope $end
$scope task write_reg $end
$var reg 5 6 addr [4:0] $end
$var reg 32 7 data [31:0] $end
$upscope $end
$scope task check $end
$var reg 32 8 got [31:0] $end
$var reg 32 9 expected [31:0] $end
$var reg 64 : test_num [63:0] $end
$upscope $end
$upscope $end
$enddefinitions $end
#0
$dumpvars
0!
1"
0#
b0 $
b0 %
b0 &
b0 '
b0 (
b0 )
b0 *
b0 +
0,
1-
0.
b0 /
b0 0
b0 1
b0 2
b0 3
b0 4
bx 5
bx 6
bx 7
bx 8
bx 9
bx :
$end
#5000
1!
1,
b0 3
b0 4
#6000
0"
1#
b101 &
b11011110101011011011111011101111 '
0-
1.
b101 1
b11011110101011011011111011101111 2
b101 6
b11011110101011011011111011101111 7
#10000
0!
0,
#15000
1!
1,
b0 3
b0 4
#16000
0#
b101 $
b11011110101011011011111011101111 (
0.
b101 /
b11011110101011011011111011101111 3
#17000
1#
b0 &
b11111111111111111111111111111111 '
b1 *
1.
b0 1
b11111111111111111111111111111111 2
b0 6
b11111111111111111111111111111111 7
b11011110101011011011111011101111 8
b11011110101011011011111011101111 9
b1 :
#20000
0!
0,
#25000
1!
1,
#26000
0#
b0 $
b0 (
0.
b0 /
b0 3
#27000
1#
b111 &
b10100101101001011010010110100101 '
b10 *
1.
b111 1
b10100101101001011010010110100101 2
b111 6
b10100101101001011010010110100101 7
b0 8
b0 9
b10 :
#30000
0!
0,
#35000
1!
1,
b0 3
b0 4
#36000
0#
b101 $
b111 %
b11011110101011011011111011101111 (
b10100101101001011010010110100101 )
0.
b101 /
b111 0
b11011110101011011011111011101111 3
b10100101101001011010010110100101 4
#37000
1#
b101 &
b10010001101000101011001111000 '
b100 *
1.
b101 1
b10010001101000101011001111000 2
b101 6
b10010001101000101011001111000 7
b10100101101001011010010110100101 8
b10100101101001011010010110100101 9
b11 :
#40000
0!
0,
#45000
1!
b10010001101000101011001111000 (
1,
b10010001101000101011001111000 3
b10100101101001011010010110100101 4
#46000
0#
b101 $
0.
#47000
1"
b101 *
1-
b10010001101000101011001111000 8
b10010001101000101011001111000 9
b100 :
#50000
0!
0,
#55000
1!
b0 (
b0 )
1,
b0 3
b0 4
#56000
0"
b101 $
b111 %
0-
#57000
b111 *
b0 8
b0 9
b101 :
