Lab9/Lab9/Lab9/Lab9.srcs/sources_1/new/alu_control.v
`timescale 1ns / 1ps



// ALUOp  (from Main Control):
//   00 = ADD  (Load / Store address calculation)
//   01 = SUB  (Branch comparison)
//   10 = R-type (decode funct3 + funct7)
//   11 = I-type ALU (decode funct3 only; funct7 ignored)


module alu_control (
    input  wire [1:0] ALUOp,
    input  wire [2:0] funct3,
    input  wire [6:0] funct7,
    output reg  [3:0] ALUControl
);

    // ALUControl output codes
    localparam ALU_AND = 4'b0000;
    localparam ALU_OR  = 4'b0001;
    localparam ALU_ADD = 4'b0010;
    localparam ALU_XOR = 4'b0011;
    localparam ALU_SUB = 4'b0110;
    localparam ALU_SLL = 4'b0100;
    localparam ALU_SRL = 4'b0101;
    localparam ALU_NOP = 4'b1111;

    always @(*) begin
        ALUControl = ALU_NOP; // default

        case (ALUOp)
        
            2'b00: ALUControl = ALU_ADD; //used for load store

            2'b01: ALUControl = ALU_SUB; // used for BEQ

            2'b10: begin
                case (funct3)
                    3'b000: ALUControl = funct7[5] ? ALU_SUB : ALU_ADD;
                    3'b001: ALUControl = ALU_SLL;
                    3'b101: ALUControl = ALU_SRL; // only SRL (funct7[5]=0)
                    3'b110: ALUControl = ALU_OR;
                    3'b111: ALUControl = ALU_AND;
                    3'b100: ALUControl = ALU_XOR;
                    default: ALUControl = ALU_NOP;
                endcase
            end

            2'b11: begin
                case (funct3)
                    3'b000: ALUControl = ALU_ADD; // ADDI
                    3'b001: ALUControl = ALU_SLL; // SLLI
                    3'b101: ALUControl = ALU_SRL; // SRLI
                    3'b110: ALUControl = ALU_OR;  // ORI
                    3'b111: ALUControl = ALU_AND; // ANDI
                    3'b100: ALUControl = ALU_XOR; // XORI
                    default: ALUControl = ALU_NOP;
                endcase
            end

            default: ALUControl = ALU_NOP;
        endcase
    end

endmodule

Lab9/Lab9/Lab9/Lab9.srcs/sources_1/new/main_control.v
`timescale 1ns / 1ps

module main_control (
    input  wire [6:0] opcode,
    output reg RegWrite,
    output reg ALUSrc,
    output reg MemRead,
    output reg MemWrite,
    output reg MemtoReg,
    output reg Branch,
    output reg [1:0] ALUOp
);

    localparam R_TYPE  = 7'b0110011;  // ADD, SUB, SLL, SRL, AND, OR, XOR
    localparam I_ALU   = 7'b0010011;  // ADDI and I types
    localparam LOAD    = 7'b0000011;  // LW, LH, LB
    localparam STORE   = 7'b0100011;  // SW, SH, SB
    localparam BRANCH  = 7'b1100011;  // BEQ

    always @(*) begin
        RegWrite = 1'b0;
        ALUSrc   = 1'b0;
        MemRead  = 1'b0;
        MemWrite = 1'b0;
        MemtoReg = 1'b0;
        Branch   = 1'b0;
        ALUOp    = 2'b00;

        case (opcode)

            // R-type: ADD, SUB, SLL, SRL, AND, OR, XOR
            //  RegWrite=1  ALUSrc=0, MemRead=0   MemWrite=0, MemtoReg=0  Branch=0, ALUOp=10 (ALU control decodes funct3/funct7)

            R_TYPE: begin
                RegWrite = 1'b1;
                ALUSrc   = 1'b0;
                MemRead  = 1'b0;
                MemWrite = 1'b0;
                MemtoReg = 1'b0;
                Branch   = 1'b0;
                ALUOp    = 2'b10;
            end

            // I-type ALU: ADDI
            // RegWrite=1  ALUSrc=1, MemRead=0 MemWrite=0 MemtoReg=0  Branch=0 ALUOp=11 (ALU control decodes funct3; funct7 ignored)
            
            I_ALU: begin
                RegWrite = 1'b1;
                ALUSrc   = 1'b1;
                MemRead  = 1'b0;
                MemWrite = 1'b0;
                MemtoReg = 1'b0;
                Branch   = 1'b0;
                ALUOp    = 2'b11;
            end

            
            // Load: LW, LH, LB
            //   RegWrite=1  ALUSrc=1 MemRead=1 MemWrite=0 MemtoReg=1  Branch=0 ALUOp=00 (ADD for address computation)
            LOAD: begin
                RegWrite = 1'b1;
                ALUSrc   = 1'b1;
                MemRead  = 1'b1;
                MemWrite = 1'b0;
                MemtoReg = 1'b1;
                Branch   = 1'b0;
                ALUOp    = 2'b00;
            end

            // Store: SW, SH, SB
            // RegWrite=0  ALUSrc=1 (base + imm address) MemRead=0 MemWrite=1 MemtoReg=X  Branch=0 ALUOp=00 (ADD for address computation)
            STORE: begin
                RegWrite = 1'b0;
                ALUSrc   = 1'b1;
                MemRead  = 1'b0;
                MemWrite = 1'b1;
                MemtoReg = 1'b0;   // dont care set to 0
                Branch   = 1'b0;
                ALUOp    = 2'b00;
            end

            // Branch: BEQ
            // RegWrite=0  ALUSrc=0 MemRead=0   MemWrite=0 MemtoReg=X  Branch=1 ALUOp=01 (SUB for comparison)
            BRANCH: begin
                RegWrite = 1'b0;
                ALUSrc   = 1'b0;
                MemRead  = 1'b0;
                MemWrite = 1'b0;
                MemtoReg = 1'b0;  // dont care set to 0
                Branch   = 1'b1;
                ALUOp    = 2'b01;
            end
            default: begin
                RegWrite = 1'b0;
                ALUSrc   = 1'b0;
                MemRead  = 1'b0;
                MemWrite = 1'b0;
                MemtoReg = 1'b0;
                Branch   = 1'b0;
                ALUOp    = 2'b00;
            end
        endcase
    end

endmodule

Lab9/Lab9/Lab9/Lab9.srcs/sim_1/new/tb_control_path.v
`timescale 1ns / 1ps


module tb_control_path;

    
    reg [6:0] opcode; // Inputs to Main Control
    wire RegWrite, ALUSrc, MemRead, MemWrite, MemtoReg, Branch; // Outputs from Main Control
    wire [1:0] ALUOp;
    
    reg [2:0] funct3; // Inputs to ALU Control
    reg [6:0] funct7;

    wire [3:0] ALUControl; // Output from ALU Control

    main_control uut_main (
        .opcode   (opcode),
        .RegWrite (RegWrite),
        .ALUSrc   (ALUSrc),
        .MemRead  (MemRead),
        .MemWrite (MemWrite),
        .MemtoReg (MemtoReg),
        .Branch   (Branch),
        .ALUOp    (ALUOp)
    );

    alu_control uut_alu (
        .ALUOp      (ALUOp),
        .funct3     (funct3),
        .funct7     (funct7),
        .ALUControl (ALUControl)
    );

    // display current signal state

    task show;
        input [127:0] instr_name; // up to 16 ASCII chars
        begin
            $display("%-8s | opcode=%b  funct3=%b  funct7[5]=%b | RW=%b AS=%b MR=%b MW=%b M2R=%b Br=%b ALUOp=%b | ALUCtrl=%b",
                     instr_name,
                     opcode, funct3, funct7[5],
                     RegWrite, ALUSrc, MemRead, MemWrite, MemtoReg, Branch, ALUOp,
                     ALUControl);
        end
    endtask

    initial begin
        $display("=======================================================");
        $display(" Lab 9 - RISC-V Control Path Simulation");
        $display("=======================================================");
        $display("%-8s | opcode         funct3  f7[5] | RW AS MR MW M2R Br ALUOp | ALUCtrl",
                 "Instr");
        $display("-----------------------------------------------------------------------");

        // ------ R-type instructions (opcode = 0110011) ------
        opcode = 7'b0110011;

        // ADD: funct3=000, funct7[5]=0
        funct3 = 3'b000; funct7 = 7'b0000000; #10; show("ADD");

        // SUB: funct3=000, funct7[5]=1
        funct3 = 3'b000; funct7 = 7'b0100000; #10; show("SUB");

        // SLL: funct3=001, funct7[5]=0
        funct3 = 3'b001; funct7 = 7'b0000000; #10; show("SLL");

        // SRL: funct3=101, funct7[5]=0
        funct3 = 3'b101; funct7 = 7'b0000000; #10; show("SRL");

        // AND: funct3=111, funct7[5]=0
        funct3 = 3'b111; funct7 = 7'b0000000; #10; show("AND");

        // OR: funct3=110, funct7[5]=0
        funct3 = 3'b110; funct7 = 7'b0000000; #10; show("OR");

        // XOR: funct3=100, funct7[5]=0
        funct3 = 3'b100; funct7 = 7'b0000000; #10; show("XOR");

        // ------ I-type ALU: ADDI (opcode = 0010011) ----------
        opcode = 7'b0010011;
        funct3 = 3'b000; funct7 = 7'b0000000; #10; show("ADDI");

        // ------ Load instructions (opcode = 0000011) ---------
        opcode = 7'b0000011;

        // LW: funct3=010
        funct3 = 3'b010; funct7 = 7'b0000000; #10; show("LW");

        // LH: funct3=001
        funct3 = 3'b001; funct7 = 7'b0000000; #10; show("LH");

        // LB: funct3=000
        funct3 = 3'b000; funct7 = 7'b0000000; #10; show("LB");

        // ------ Store instructions (opcode = 0100011) --------
        opcode = 7'b0100011;

        // SW: funct3=010
        funct3 = 3'b010; funct7 = 7'b0000000; #10; show("SW");

        // SH: funct3=001
        funct3 = 3'b001; funct7 = 7'b0000000; #10; show("SH");

        // SB: funct3=000
        funct3 = 3'b000; funct7 = 7'b0000000; #10; show("SB");

        // ------ Branch: BEQ (opcode = 1100011) ---------------
        opcode = 7'b1100011;
        funct3 = 3'b000; funct7 = 7'b0000000; #10; show("BEQ");

        // ------ Illegal / unknown opcode ---------------------
        opcode = 7'b1111111;
        funct3 = 3'b000; funct7 = 7'b0000000; #10; show("ILLEGAL");

        $display("=======================================================");
        $display(" Simulation complete.");
        $display("=======================================================");
        $finish;
    end

    initial begin
        $dumpfile("tb_control_path.vcd");
        $dumpvars(0, tb_control_path);
    end

endmodule

Lab9/Lab9/Lab9/Lab9.sim/sim_1/behav/xsim/tb_control_path.vcd
$date
   Tue Mar 17 10:28:24 2026
$end
$version
  2020.1
$end
$timescale
  1ps
$end
$scope module tb_control_path $end
$var reg 7 ! opcode [6:0] $end
$var wire 1 " RegWrite $end
$var wire 1 # ALUSrc $end
$var wire 1 $ MemRead $end
$var wire 1 % MemWrite $end
$var wire 1 & MemtoReg $end
$var wire 1 ' Branch $end
$var wire 2 ( ALUOp [1:0] $end
$var reg 3 ) funct3 [2:0] $end
$var reg 7 * funct7 [6:0] $end
$var wire 4 + ALUControl [3:0] $end
$scope module uut_main $end
$var wire 7 , opcode [6:0] $end
$var reg 1 - RegWrite $end
$var reg 1 . ALUSrc $end
$var reg 1 / MemRead $end
$var reg 1 0 MemWrite $end
$var reg 1 1 MemtoReg $end
$var reg 1 2 Branch $end
$var reg 2 3 ALUOp [1:0] $end
$var parameter 7 4 R_TYPE [6:0] $end
$var parameter 7 5 I_ALU [6:0] $end
$var parameter 7 6 LOAD [6:0] $end
$var parameter 7 7 STORE [6:0] $end
$var parameter 7 8 BRANCH [6:0] $end
$upscope $end
$scope module uut_alu $end
$var wire 2 ( ALUOp [1:0] $end
$var wire 3 9 funct3 [2:0] $end
$var wire 7 : funct7 [6:0] $end
$var reg 4 ; ALUControl [3:0] $end
$var parameter 4 < ALU_AND [3:0] $end
$var parameter 4 = ALU_OR [3:0] $end
$var parameter 4 > ALU_ADD [3:0] $end
$var parameter 4 ? ALU_XOR [3:0] $end
$var parameter 4 @ ALU_SUB [3:0] $end
$var parameter 4 A ALU_SLL [3:0] $end
$var parameter 4 B ALU_SRL [3:0] $end
$var parameter 4 C ALU_NOP [3:0] $end
$upscope $end
$scope task show $end
$var reg 128 D instr_name [127:0] $end
$upscope $end
$upscope $end
$enddefinitions $end
#0
$dumpvars
b110011 !
1"
0#
0$
0%
0&
0'
b10 (
b0 )
b0 *
b10 +
b110011 ,
1-
0.
0/
00
01
02
b10 3
b110011 4
b10011 5
b11 6
b100011 7
b1100011 8
b0 9
b0 :
b10 ;
b0 <
b1 =
b10 >
b11 ?
b110 @
b100 A
b101 B
b1111 C
bx D
$end
#10000
b0 )
b100000 *
b110 +
b100000 :
b110 ;
b10000010100010001000100 D
#20000
b1 )
b0 *
b100 +
b1 9
b0 :
b100 ;
b10100110101010101000010 D
#30000
b101 )
b0 *
b101 +
b101 9
b101 ;
b10100110100110001001100 D
#40000
b111 )
b0 *
b0 +
b111 9
b0 ;
b10100110101001001001100 D
#50000
b110 )
b0 *
b1 +
b110 9
b1 ;
b10000010100111001000100 D
#60000
b100 )
b0 *
b11 +
b100 9
b11 ;
b100111101010010 D
#70000
b10011 !
1#
b11 (
b0 )
b0 *
b10 +
b10011 ,
1-
1.
0/
00
01
02
b11 3
b0 9
b10 ;
b10110000100111101010010 D
#80000
b11 !
1$
1&
b0 (
b10 )
b0 *
b10 +
b11 ,
1-
1.
1/
00
11
02
b0 3
b10 9
b10 ;
b1000001010001000100010001001001 D
#90000
b1 )
b0 *
b1 9
b10 ;
b100110001010111 D
#100000
b0 )
b0 *
b0 9
b10 ;
b100110001001000 D
#110000
b100011 !
0"
0$
1%
0&
b10 )
b0 *
b100011 ,
0-
1.
0/
10
01
02
b0 3
b10 9
b10 ;
b100110001000010 D
#120000
b1 )
b0 *
b1 9
b10 ;
b101001101010111 D
#130000
b0 )
b0 *
b0 9
b10 ;
b101001101001000 D
#140000
b1100011 !
0#
0%
1'
b1 (
b0 )
b0 *
b110 +
b1100011 ,
0-
0.
0/
00
01
12
b1 3
b110 ;
b101001101000010 D
#150000
b1111111 !
0'
b0 (
b0 )
b0 *
b10 +
b1111111 ,
0-
0.
0/
00
01
02
b0 3
b10 ;
b10000100100010101010001 D
#160000
b1001001010011000100110001000101010001110100000101001100 D
