Project/PartB/lab11/lab11.srcs/sources_1/new/ImmGen.v
`timescale 1ns / 1ps

module immGen (
    input  wire [31:0] inst,
    output reg  [31:0] imm_out
);

    wire [6:0] opcode = inst[6:0];

    always @(*) begin
        case (opcode)
            // I-type: LOAD, OP-IMM, JALR
            7'b0000011,          // LOAD
            7'b0010011,          // OP-IMM (ADDI, SLTI, etc.)
            7'b1100111:          // JALR
                imm_out = {{20{inst[31]}}, inst[31:20]};

            // S-type: STORE
            7'b0100011:
                imm_out = {{20{inst[31]}}, inst[31:25], inst[11:7]};

            // B-type: BRANCH
            7'b1100011:
                imm_out = {{19{inst[31]}}, inst[31], inst[7], inst[30:25], inst[11:8], 1'b0};

            // U-type: LUI, AUIPC  (upper immediate)
            7'b0110111,          // LUI
            7'b0010111:          // AUIPC
                imm_out = {inst[31:12], 12'b0};

            // J-type: JAL
            7'b1101111:
                imm_out = {{11{inst[31]}}, inst[31], inst[19:12], inst[20], inst[30:21], 1'b0};

            default:
                imm_out = 32'b0;
        endcase
    end

endmodule

Project/PartC/Project_Taskc/lab11_secondzip/lab11/lab11.srcs/sources_1/new/Mux2.v
`timescale 1ns / 1ps

module mux2 #(
    parameter WIDTH = 32
)(
    input  wire [WIDTH-1:0] in0,   // Input 0: PC + 4
    input  wire [WIDTH-1:0] in1,   // Input 1: branch target
    input  wire  sel,   // PCSrc control signal
    output wire [WIDTH-1:0] out
);

    assign out = sel ? in1 : in0;

endmodule

Project/PartB/lab11/lab11.srcs/sources_1/new/Branchadder.v
`timescale 1ns / 1ps


module branchAdder (
    input  wire [31:0] pc,
    input  wire [31:0] imm,       //sign extended immediate from immGen
    output wire [31:0] branch_target
);

    // Per RV32I spec: branch offset = imm << 1
    assign branch_target = pc + imm;

endmodule

Project/PartB/lab11/lab11.srcs/sources_1/new/Pcadder.v
`timescale 1ns / 1ps

module pcAdder (
    input  wire [31:0] pc,
    output wire [31:0] pc_plus4
);

    assign pc_plus4 = pc + 32'd4;

endmodule

Lab11/lab11/lab11.srcs/sources_1/new/Programcounter.v
`timescale 1ns / 1ps

module ProgramCounter (
    input  wire        clk,
    input  wire        reset,
    input  wire [31:0] pc_next,   // Next PC value (from mux2)
    output reg  [31:0] pc         // Current PC value
);

    always @(posedge clk) begin
        if (reset)
            pc <= 32'b0;
        else
            pc <= pc_next;
    end

endmodule

Project/PartB/lab11/lab11.srcs/sim_1/new/tb_task1.v
`timescale 1ns / 1ps

module tb_Task1;

    reg clk;
    reg reset;

    initial clk = 0;
    always #5 clk = ~clk;   // 10 ns period -> 100 MHz

    wire [31:0] pc;
    wire [31:0] pc_plus4;
    wire [31:0] branch_target;
    wire [31:0] pc_next;

    // Control
    reg  PCSrc;

    // Immediate generation
    reg  [31:0] inst;
    wire [31:0] imm_out;

    ProgramCounter uPC (
        .clk     (clk),
        .reset   (reset),
        .pc_next (pc_next),
        .pc      (pc)
    );

    pcAdder uPCAdder (
        .pc      (pc),
        .pc_plus4(pc_plus4)
    );

    branchAdder uBranchAdder (
        .pc            (pc),
        .imm           (imm_out),
        .branch_target (branch_target)
    );

    mux2 #(.WIDTH(32)) uMux (
        .in0 (pc_plus4),
        .in1 (branch_target),
        .sel (PCSrc),
        .out (pc_next)
    );

    immGen uImmGen (
        .inst    (inst),
        .imm_out (imm_out)
    );

    task check;
        input [31:0] actual;
        input [31:0] expected;
        input [127:0] label;
        begin
            if (actual === expected)
                $display("PASS  %s : got 0x%08h", label, actual);
            else
                $display("FAIL  %s : expected 0x%08h, got 0x%08h", label, expected, actual);
        end
    endtask

    
    integer i;

    initial begin
        // Reset
        reset  = 1;
        PCSrc  = 0;
        inst   = 32'b0;
        @(posedge clk); #1;
        reset  = 0;

        $display("\n--- Sequential PC increment (PCSrc = 0) ---");
        for (i = 0; i < 5; i = i + 1) begin
            @(posedge clk); #1;
            $display("  PC = 0x%08h  (expected 0x%08h)", pc, (i+1)*4);
        end
        check(pc, 32'd20, "PC after 5 increments");

        //    Use ADDI x0,x0,8  
        $display("\n--- Branch taken (PCSrc = 1) ---");
        inst   = {12'd8, 5'd0, 3'b000, 5'd0, 7'b0010011}; // ADDI imm=8
        PCSrc  = 1;
        @(posedge clk); #1;
        $display("  PC = 0x%08h  branch_target was 0x%08h", pc, 32'd36);
        check(pc, 32'd36, "PC after branch (20 + 8<<1)");

        PCSrc = 0;
        @(posedge clk); #1;
        check(pc, 32'd40, "PC sequential after branch");

        //    ADDI x1, x2, -5  
        $display("\n--- Immediate Generation ---");
        inst = {12'hFFB, 5'd2, 3'b000, 5'd1, 7'b0010011}; // ADDI x1,x2,-5
        #1;
        check(imm_out, 32'hFFFFFFFB, "I-type imm (-5)");

        // I-type positive: ADDI x3,x4,100
        inst = {12'd100, 5'd4, 3'b000, 5'd3, 7'b0010011};
        #1;
        check(imm_out, 32'd100, "I-type imm (+100)");

        // LOAD: LW x5, 12(x6)
        inst = {12'd12, 5'd6, 3'b010, 5'd5, 7'b0000011};
        #1;
        check(imm_out, 32'd12, "I-type LOAD imm (12)");

        //    SW x7, -3(x8)  
        inst = {7'h7F, 5'd7, 5'd8, 3'b010, 5'h1D, 7'b0100011}; // SW imm=-3
        #1;
        check(imm_out, 32'hFFFFFFFD, "S-type imm (-3)");

        // SW x9, 20(x10)
        inst = {7'b0000000, 5'd9, 5'd10, 3'b010, 5'b10100, 7'b0100011};
        #1;
        check(imm_out, 32'd20, "S-type imm (+20)");

        //    BEQ x1,x2, +16  
        inst = {1'b0, 6'b000000, 5'd2, 5'd1, 3'b000, 4'b1000, 1'b0, 7'b1100011};
        #1;
        check(imm_out, 32'd16, "B-type imm (+16)");

        // BNE with negative offset: offset = -8
        inst = {1'b1, 6'b111111, 5'd2, 5'd1, 3'b001, 4'b1100, 1'b1, 7'b1100011};
        #1;
        check(imm_out, 32'hFFFFFFF8, "B-type imm (-8)");

        $display("\n--- Simulation complete ---\n");
        $finish;
    end

    // Optional waveform dump
    initial begin
        $dumpfile("tb_Task1.vcd");
        $dumpvars(0, tb_Task1);
    end

endmodule

Lab11/lab11/lab11.sim/sim_1/behav/xsim/tb_Task1.vcd
$date
   Tue Mar 31 12:34:52 2026
$end
$version
  2020.1
$end
$timescale
  1ps
$end
$scope module tb_Task1 $end
$var reg 1 ! clk $end
$var reg 1 " reset $end
$var wire 32 # pc [31:0] $end
$var wire 32 $ pc_plus4 [31:0] $end
$var wire 32 % branch_target [31:0] $end
$var wire 32 & pc_next [31:0] $end
$var reg 1 ' PCSrc $end
$var reg 32 ( inst [31:0] $end
$var wire 32 ) imm_out [31:0] $end
$var integer 32 * i $end
$scope module uPC $end
$var wire 1 + clk $end
$var wire 1 , reset $end
$var wire 32 & pc_next [31:0] $end
$var reg 32 - pc [31:0] $end
$upscope $end
$scope module uPCAdder $end
$var wire 32 # pc [31:0] $end
$var wire 32 $ pc_plus4 [31:0] $end
$upscope $end
$scope module uBranchAdder $end
$var wire 32 # pc [31:0] $end
$var wire 32 ) imm [31:0] $end
$var wire 32 % branch_target [31:0] $end
$upscope $end
$scope module uMux $end
$var wire 32 $ in0 [31:0] $end
$var wire 32 % in1 [31:0] $end
$var wire 1 . sel $end
$var wire 32 & out [31:0] $end
$var parameter 32 / WIDTH [31:0] $end
$upscope $end
$scope module uImmGen $end
$var wire 32 0 inst [31:0] $end
$var reg 32 1 imm_out [31:0] $end
$var wire 7 2 opcode [6:0] $end
$upscope $end
$scope task check $end
$var reg 32 3 actual [31:0] $end
$var reg 32 4 expected [31:0] $end
$var reg 128 5 label [127:0] $end
$upscope $end
$upscope $end
$enddefinitions $end
#0
$dumpvars
0!
1"
bx #
bx $
bx %
bx &
0'
b0 (
b0 )
bx *
0+
1,
bx -
0.
b100000 /
b0 0
b0 1
b0 2
bx 3
bx 4
bx 5
$end
#5000
1!
b0 #
b100 $
b0 %
b100 &
1+
b0 -
#6000
0"
b0 *
0,
#10000
0!
0+
#15000
1!
b100 #
b1000 $
b100 %
b1000 &
1+
b100 -
#16000
b1 *
#20000
0!
0+
#25000
1!
b1000 #
b1100 $
b1000 %
b1100 &
1+
b1000 -
#26000
b10 *
#30000
0!
0+
#35000
1!
b1100 #
b10000 $
b1100 %
b10000 &
1+
b1100 -
#36000
b11 *
#40000
0!
0+
#45000
1!
b10000 #
b10100 $
b10000 %
b10100 &
1+
b10000 -
#46000
b100 *
#50000
0!
0+
#55000
1!
b10100 #
b11000 $
b10100 %
b11000 &
1+
b10100 -
#56000
b11100 %
b11100 &
1'
b100000000000000000010011 (
b1000 )
b101 *
1.
b100000000000000000010011 0
b1000 1
b10011 2
b10100 3
b10100 4
b1110100011001010111001000100000001101010010000001101001011011100110001101110010011001010110110101100101011011100111010001110011 5
#60000
0!
0+
#65000
1!
b11100 #
b100000 $
b100100 %
b100100 &
1+
b11100 -
#66000
b100000 &
0'
0.
b11100 3
b100100 4
b1100001011011100110001101101000001000000010100000110010001100000010000000101011001000000011100000111100001111000011000100101001 5
#70000
0!
0+
#75000
1!
b100000 #
b100100 $
b101000 %
b100100 &
1+
b100000 -
#76000
b11011 %
b11111111101100010000000010010011 (
b11111111111111111111111111111011 )
b11111111101100010000000010010011 0
b11111111111111111111111111111011 1
b100000 3
b101000 4
b1101001011000010110110000100000011000010110011001110100011001010111001000100000011000100111001001100001011011100110001101101000 5
#77000
b10000100 %
b110010000100000000110010011 (
b1100100 )
b110010000100000000110010011 0
b1100100 1
b11111111111111111111111111111011 3
b11111111111111111111111111111011 4
b10010010010110101110100011110010111000001100101001000000110100101101101011011010010000000101000001011010011010100101001 5
#78000
b101100 %
b110000110010001010000011 (
b1100 )
b110000110010001010000011 0
b1100 1
b11 2
b1100100 3
b1100100 4
b101101011101000111100101110000011001010010000001101001011011010110110100100000001010000010101100110001001100000011000000101001 5
#79000
b11101 %
b11111110011101000010111010100011 (
b11111111111111111111111111111101 )
b11111110011101000010111010100011 0
b11111111111111111111111111111101 1
b100011 2
b1100 3
b1100 4
b1110000011001010010000001001100010011110100000101000100001000000110100101101101011011010010000000101000001100010011001000101001 5
#80000
0!
b110100 %
b100101010010101000100011 (
b10100 )
0+
b100101010010101000100011 0
b10100 1
b11111111111111111111111111111101 3
b11111111111111111111111111111101 4
b10100110010110101110100011110010111000001100101001000000110100101101101011011010010000000101000001011010011001100101001 5
#81000
b110000 %
b1000001000100001100011 (
b10000 )
b1000001000100001100011 0
b10000 1
b1100011 2
b10100 3
b10100 4
b1010011001011010111010001111001011100000110010100100000011010010110110101101101001000000010100000101011001100100011000000101001 5
#82000
b11000 %
b11111110001000001001110011100011 (
b11111111111111111111111111111000 )
b11111110001000001001110011100011 0
b11111111111111111111111111111000 1
b10000 3
b10000 4
b1000010001011010111010001111001011100000110010100100000011010010110110101101101001000000010100000101011001100010011011000101001 5
#83000
b11111111111111111111111111111000 3
b11111111111111111111111111111000 4
b10000100010110101110100011110010111000001100101001000000110100101101101011011010010000000101000001011010011100000101001 5
