Lab7/lab7_friday/lab7_friday.srcs/sources_1/new/ALU.v
`timescale 1ns / 1ps
 
module alu(
    input  [31:0] A,
    input  [31:0] B,
    input  [3:0]  ALUControl,
    output reg [31:0] ALUResult,
    output Zero
);
 
    always @(*) begin
        case (ALUControl)
            4'b0000: ALUResult = A + B;                // ADD
            4'b0001: ALUResult = A - B;                // SUB
            4'b0010: ALUResult = A & B;                // AND
            4'b0011: ALUResult = A | B;                // OR
            4'b0100: ALUResult = A ^ B;                // XOR
            4'b0101: ALUResult = A << B[4:0];          // SLL
            4'b0110: ALUResult = A >> B[4:0];          // SRL
            4'b0111: ALUResult = A - B;                // BEQ uses subtraction
            default: ALUResult = 32'b0;
        endcase
    end
 
    assign Zero = (ALUResult == 32'b0);
 
endmodule

Lab7/lab7_friday/lab7/lab7.srcs/sources_1/new/RegisterFile.v
`timescale 1ns / 1ps

module RegisterFile (
    input clk,
    input rst,
    input WriteEnable,
    input [4:0] rs1,
    input [4:0] rs2,
    input [4:0] rd,
    input [31:0] WriteData,
    output reg [31:0] ReadData1,
    output reg [31:0] ReadData2
);

    reg [31:0] regs [31:0];
    integer i;

    //Synchronous write and reset
    always @(posedge clk) begin
        //Clear all registers on reset
        if (rst) begin
            for (i = 0; i < 32; i = i + 1)
                regs[i] <= 32'b0;
        end else begin
            //Write only if enabled and destination is not x0
            if (WriteEnable && (rd != 5'b0))
                regs[rd] <= WriteData;
        end
    end

    //Asynchronous reads
    reg [31:0] ReadData1, ReadData2;

    always @(*) begin
        if (rs1 == 5'b0)
            ReadData1 = 32'b0;
        else
            ReadData1 = regs[rs1];
    end

    always @(*) begin
        if(rs2==5'b0)
            ReadData2=32'b0;
        else
            ReadData2=regs[rs2];
    end

endmodule

Lab7/lab7_friday/lab7/lab7.srcs/sources_1/new/FSM.v
`timescale 1ns / 1ps

module FSM (
    input        clk,
    input        rst,
    input        ALU_Zero,          // from ALU, used in BEQ_CHECK state
    input [31:0] ALU_Result,        // from ALU, written into destination register

    output reg WE,                  // RegisterFile WriteEnable
    output reg [4:0]  rs1,          // RegisterFile read address 1
    output reg [4:0]  rs2,          // RegisterFile read address 2
    output reg [4:0]  rd,           // RegisterFile write address
    output reg [31:0] WriteData,    // RegisterFile write data
    output reg [3:0]  ALUControl,   // ALU operation select
    output reg [4:0]  state         // states
);

    //State Encoding
    localparam [4:0]
        IDLE       = 5'd0,
        WRITE_X1   = 5'd1,
        WRITE_X2   = 5'd2,
        WRITE_X3   = 5'd3,
        ALU_ADD    = 5'd4,
        ALU_SUB    = 5'd5,
        ALU_AND    = 5'd6,
        ALU_OR     = 5'd7,
        ALU_XOR    = 5'd8,
        ALU_SLL    = 5'd9,
        ALU_SRL    = 5'd10,
        BEQ_CHECK  = 5'd11,
        RAW_WRITE  = 5'd12,
        RAW_READ   = 5'd13,
        DONE       = 5'd14;

    reg [4:0] next_state;

    // State Register(sequential)
    always @(posedge clk) begin
        if (rst)
            state <= IDLE;
        else
            state <= next_state;
    end

    // Next-State Logic(combinational)
    always @(*) begin
        if (state == IDLE) begin
            next_state = WRITE_X1;
        end
        else if (state == WRITE_X1) begin
            next_state = WRITE_X2;
        end
        else if (state == WRITE_X2) begin
            next_state = WRITE_X3;
        end
        else if (state == WRITE_X3) begin
            next_state = ALU_ADD;
        end
        else if (state == ALU_ADD) begin
            next_state = ALU_SUB;
        end
        else if (state == ALU_SUB) begin
            next_state = ALU_AND;
        end
        else if (state == ALU_AND) begin
            next_state = ALU_OR;
        end
        else if (state == ALU_OR) begin
            next_state = ALU_XOR;
        end
        else if (state == ALU_XOR) begin
            next_state = ALU_SLL;
        end
        else if (state == ALU_SLL) begin
            next_state = ALU_SRL;
        end
        else if (state == ALU_SRL) begin
            next_state = BEQ_CHECK;
        end
        else if (state == BEQ_CHECK) begin
            next_state = RAW_WRITE;
        end
        else if (state == RAW_WRITE) begin
            next_state = RAW_READ;
        end
        else if (state == RAW_READ) begin
            next_state = DONE;
        end
        else begin
            next_state = DONE;
        end
    end

    //Output Logic(combinational)
    always @(*) begin
        // Safe defaults
        WE         = 1'b0;
        rs1        = 5'd0;
        rs2        = 5'd0;
        rd         = 5'd0;
        WriteData  = 32'b0;
        ALUControl = 4'b0000;

        if (state == WRITE_X1) begin
            WE        = 1'b1;
            rd        = 5'd1;
            WriteData = 32'h10101010;
        end
        else if (state == WRITE_X2) begin
            WE        = 1'b1;
            rd        = 5'd2;
            WriteData = 32'h01010101;
        end
        else if (state == WRITE_X3) begin
            WE        = 1'b1;
            rd        = 5'd3;
            WriteData = 32'h00000005;
        end
        else if (state == ALU_ADD) begin
            rs1        = 5'd1;
            rs2        = 5'd2;
            ALUControl = 4'b0000; //add
            WE         = 1'b1;
            rd         = 5'd4;
            WriteData  = ALU_Result;
        end
        else if (state == ALU_SUB) begin
            rs1        = 5'd1;
            rs2        = 5'd2;
            ALUControl = 4'b0001; //sub
            WE         = 1'b1;
            rd         = 5'd5;
            WriteData  = ALU_Result;
        end
        else if (state == ALU_AND) begin
            rs1        = 5'd1;
            rs2        = 5'd2;
            ALUControl = 4'b0010; //and
            WE         = 1'b1;
            rd         = 5'd6;
            WriteData  = ALU_Result;
        end
        else if (state == ALU_OR) begin
            rs1        = 5'd1;
            rs2        = 5'd2;
            ALUControl = 4'b0011; //or
            WE         = 1'b1;
            rd         = 5'd7;
            WriteData  = ALU_Result;
        end
        else if (state == ALU_XOR) begin
            rs1        = 5'd1;
            rs2        = 5'd2;
            ALUControl = 4'b0100; //xor
            WE         = 1'b1;
            rd         = 5'd8;
            WriteData  = ALU_Result;
        end
        else if (state == ALU_SLL) begin
            rs1        = 5'd1;
            rs2        = 5'd3;      
            ALUControl = 4'b0101; //shift left logic
            WE         = 1'b1;
            rd         = 5'd9;
            WriteData  = ALU_Result;
        end
        else if (state == ALU_SRL) begin
            rs1        = 5'd1;
            rs2        = 5'd3;      
            ALUControl = 4'b0110;   //shift right logic
            WE         = 1'b1;
            rd         = 5'd10;
            WriteData  = ALU_Result;
        end
        else if (state == BEQ_CHECK) begin
            rs1        = 5'd1;
            rs2        = 5'd1;      
            ALUControl = 4'b0111;   //beq
            WE         = 1'b1;
            rd         = 5'd11;
            if (ALU_Zero)
                WriteData = 32'h00000001;
            else
                WriteData = 32'h00000000;
        end
        else if (state == RAW_WRITE) begin
            WE        = 1'b1;
            rd        = 5'd12;
            WriteData = 32'hABCDABCD;
        end
        else if (state == RAW_READ) begin
            rs1 = 5'd12;            // result on ReadData1
        end
      
    end

endmodule

Lab7/lab7_friday/lab7/lab7.srcs/sources_1/new/RF_ALU_FSM.v
`timescale 1ns / 1ps

module RF_ALU_FSM (
    input  clk,
    input  rst,

    output [31:0] ReadData1,    // RF read port 1 
    output [31:0] ReadData2,    // RF read port 2 
    output [31:0] ALU_Result,   // ALU output
    output        ALU_Zero,     // ALU zero flag
    output [4:0]  state         // FSM current state
);

    wire        WE;
    wire [4:0]  rs1, rs2, rd;
    wire [31:0] WriteData;
    wire [3:0]  ALUControl;

    // Instantiate FSM
    FSM fsm_inst (
        .clk (clk),
        .rst (rst),
        .ALU_Zero (ALU_Zero),
        .ALU_Result (ALU_Result),
        .WE (WE),
        .rs1 (rs1),
        .rs2 (rs2),
        .rd (rd),
        .WriteData (WriteData),
        .ALUControl (ALUControl),
        .state (state)
    );

    // Instantiate Register File
    RegisterFile rf_inst (
        .clk (clk),
        .rst (rst),
        .WriteEnable(WE),
        .rs1 (rs1),
        .rs2 (rs2),
        .rd (rd),
        .WriteData (WriteData),
        .ReadData1 (ReadData1),
        .ReadData2  (ReadData2)
    );

    // Instantiate ALU
    alu alu_inst (
        .A (ReadData1),
        .B (ReadData2),
        .ALUControl (ALUControl),
        .ALUResult (ALU_Result),
        .Zero (ALU_Zero)
    );

endmodule

Lab7/lab7_friday/lab7_friday.srcs/sim_1/new/RF_ALU_FSM_tb.v
`timescale 1ns / 1ps

module RF_ALU_FSM_tb;

    // Clock and reset
    reg clk, rst;
    initial clk = 0;
    always #5 clk = ~clk;

    // DUT outputs
    wire [31:0] ReadData1;
    wire [31:0] ReadData2;
    wire [31:0] ALU_Result;
    wire ALU_Zero;
    wire [4:0]  state;

    //Instantiate DUT
    RF_ALU_FSM dut (
        .clk (clk),
        .rst (rst),
        .ReadData1 (ReadData1),
        .ReadData2 (ReadData2),
        .ALU_Result(ALU_Result),
        .ALU_Zero (ALU_Zero),
        .state (state)
    );

    integer pass_count;
    integer fail_count;

    initial begin
        pass_count = 0;
        fail_count = 0;

        //Hold reset high for 2 cycles to clear all registers
        rst = 1;
        @(posedge clk);
        @(posedge clk);
        #1;
        rst = 0;
        
        //TEST CASES

        //Wait for FSM to finish all state transitions
        repeat(16) @(posedge clk);
        #1;
        
        force dut.rs1 = 5'd4; #1;
        if (ReadData1 === 32'h11111111)
            begin $display("PASS [ADD  x4]: 0x%08h", ReadData1); pass_count = pass_count + 1; end
        else
            begin $display("FAIL [ADD  x4]: expected 0x11111111  got 0x%08h", ReadData1); fail_count = fail_count + 1; end

        force dut.rs1 = 5'd5; #1;
        if (ReadData1 === 32'h0F0F0F0F)
            begin $display("PASS [SUB  x5]: 0x%08h", ReadData1); pass_count = pass_count + 1; end
        else
            begin $display("FAIL [SUB  x5]: expected 0x0f0f0f0f  got 0x%08h", ReadData1); fail_count = fail_count + 1; end

        force dut.rs1 = 5'd6; #1;
        if (ReadData1 === 32'h00000000)
            begin $display("PASS [AND  x6]: 0x%08h", ReadData1); pass_count = pass_count + 1; end
        else
            begin $display("FAIL [AND  x6]: expected 0x00000000  got 0x%08h", ReadData1); fail_count = fail_count + 1; end

        force dut.rs1 = 5'd7; #1;
        if (ReadData1 === 32'h11111111)
            begin $display("PASS [OR   x7]: 0x%08h", ReadData1); pass_count = pass_count + 1; end
        else
            begin $display("FAIL [OR   x7]: expected 0x11111111  got 0x%08h", ReadData1); fail_count = fail_count + 1; end

        force dut.rs1 = 5'd8; #1;
        if (ReadData1 === 32'h11111111)
            begin $display("PASS [XOR  x8]: 0x%08h", ReadData1); pass_count = pass_count + 1; end
        else
            begin $display("FAIL [XOR  x8]: expected 0x11111111  got 0x%08h", ReadData1); fail_count = fail_count + 1; end

        force dut.rs1 = 5'd9; #1;
        if (ReadData1 === 32'h02020200)
            begin $display("PASS [SLL  x9]: 0x%08h", ReadData1); pass_count = pass_count + 1; end
        else
            begin $display("FAIL [SLL  x9]: expected 0x02020200  got 0x%08h", ReadData1); fail_count = fail_count + 1; end

        force dut.rs1 = 5'd10; #1;
        if (ReadData1 === 32'h00808080)
            begin $display("PASS [SRL x10]: 0x%08h", ReadData1); pass_count = pass_count + 1; end
        else
            begin $display("FAIL [SRL x10]: expected 0x00808080  got 0x%08h", ReadData1); fail_count = fail_count + 1; end

        force dut.rs1 = 5'd11; #1;
        if (ReadData1 === 32'h00000001)
            begin $display("PASS [BEQ x11]: 0x%08h", ReadData1); pass_count = pass_count + 1; end
        else
            begin $display("FAIL [BEQ x11]: expected 0x00000001  got 0x%08h", ReadData1); fail_count = fail_count + 1; end

        force dut.rs1 = 5'd12; #1;
        if (ReadData1 === 32'hABCDABCD)
            begin $display("PASS [RAW x12]: 0x%08h", ReadData1); pass_count = pass_count + 1; end
        else
            begin $display("FAIL [RAW x12]: expected 0xabcdabcd  got 0x%08h", ReadData1); fail_count = fail_count + 1; end

        force dut.rs1 = 5'd0; #1;
        if (ReadData1 === 32'h00000000)
            begin $display("PASS [x0 = 0 ]: 0x%08h", ReadData1); pass_count = pass_count + 1; end
        else
            begin $display("FAIL [x0 = 0 ]: expected 0x00000000  got 0x%08h", ReadData1); fail_count = fail_count + 1; end

        // Release force so DUT returns to normal
        release dut.rs1;

        $display("-------------------------------");
        $display("Total: %0d PASSED, %0d FAILED", pass_count, fail_count);
        $display("-------------------------------");
        $finish;
    end

    //Dump waveforms
    initial begin
        $dumpfile("RF_ALU_FSM_tb.vcd");
        $dumpvars(0, RF_ALU_FSM_tb);
    end

    //Print state and ALU result every clock cycle
    always @(posedge clk) begin
        if (!rst)
            $display("t=%0t  state=%0d  ALU_Result=0x%08h  Zero=%b",
                     $time, state, ALU_Result, ALU_Zero);
    end

endmodule

Lab7/lab7_friday/lab7_friday.sim/sim_1/behav/xsim/RF_ALU_FSM_tb.vcd
$date
   Fri Mar  6 22:59:42 2026
$end
$version
  2020.1
$end
$timescale
  1ps
$end
$scope module RF_ALU_FSM_tb $end
$var reg 1 ! clk $end
$var reg 1 " rst $end
$var wire 32 # ReadData1 [31:0] $end
$var wire 32 $ ReadData2 [31:0] $end
$var wire 32 % ALU_Result [31:0] $end
$var wire 1 & ALU_Zero $end
$var wire 5 ' state [4:0] $end
$var integer 32 ( pass_count $end
$var integer 32 ) fail_count $end
$scope module dut $end
$var wire 1 * clk $end
$var wire 1 + rst $end
$var wire 32 # ReadData1 [31:0] $end
$var wire 32 $ ReadData2 [31:0] $end
$var wire 32 % ALU_Result [31:0] $end
$var wire 1 & ALU_Zero $end
$var wire 5 ' state [4:0] $end
$var wire 1 , WE $end
$var wire 5 - rs1 [4:0] $end
$var wire 5 . rs2 [4:0] $end
$var wire 5 / rd [4:0] $end
$var wire 32 0 WriteData [31:0] $end
$var wire 4 1 ALUControl [3:0] $end
$scope module fsm_inst $end
$var wire 1 * clk $end
$var wire 1 + rst $end
$var wire 1 & ALU_Zero $end
$var wire 32 % ALU_Result [31:0] $end
$var reg 1 2 WE $end
$var reg 5 3 rs1 [4:0] $end
$var reg 5 4 rs2 [4:0] $end
$var reg 5 5 rd [4:0] $end
$var reg 32 6 WriteData [31:0] $end
$var reg 4 7 ALUControl [3:0] $end
$var reg 5 8 state [4:0] $end
$var reg 5 9 next_state [4:0] $end
$var parameter 5 : IDLE [4:0] $end
$var parameter 5 ; WRITE_X1 [4:0] $end
$var parameter 5 < WRITE_X2 [4:0] $end
$var parameter 5 = WRITE_X3 [4:0] $end
$var parameter 5 > ALU_ADD [4:0] $end
$var parameter 5 ? ALU_SUB [4:0] $end
$var parameter 5 @ ALU_AND [4:0] $end
$var parameter 5 A ALU_OR [4:0] $end
$var parameter 5 B ALU_XOR [4:0] $end
$var parameter 5 C ALU_SLL [4:0] $end
$var parameter 5 D ALU_SRL [4:0] $end
$var parameter 5 E BEQ_CHECK [4:0] $end
$var parameter 5 F RAW_WRITE [4:0] $end
$var parameter 5 G RAW_READ [4:0] $end
$var parameter 5 H DONE [4:0] $end
$upscope $end
$scope module rf_inst $end
$var wire 1 * clk $end
$var wire 1 + rst $end
$var wire 1 , WriteEnable $end
$var wire 5 - rs1 [4:0] $end
$var wire 5 . rs2 [4:0] $end
$var wire 5 / rd [4:0] $end
$var wire 32 0 WriteData [31:0] $end
$var reg 32 I ReadData1 [31:0] $end
$var reg 32 J ReadData2 [31:0] $end
$var integer 32 K i $end
$upscope $end
$scope module alu_inst $end
$var wire 32 # A [31:0] $end
$var wire 32 $ B [31:0] $end
$var wire 4 1 ALUControl [3:0] $end
$var reg 32 L ALUResult [31:0] $end
$var wire 1 & Zero $end
$upscope $end
$upscope $end
$upscope $end
$enddefinitions $end
#0
$dumpvars
0!
1"
bx #
bx $
bx %
x&
bx '
b0 (
b0 )
0*
1+
x,
bx -
bx .
bx /
bx 0
bx 1
x2
bx 3
bx 4
bx 5
bx 6
bx 7
bx 8
bx 9
b0 :
b1 ;
b10 <
b11 =
b100 >
b101 ?
b110 @
b111 A
b1000 B
b1001 C
b1010 D
b1011 E
b1100 F
b1101 G
b1110 H
bx I
bx J
bx K
bx L
$end
#5000
1!
b0 #
b0 $
b0 %
1&
b0 '
1*
0,
b0 -
b0 .
b0 /
b0 0
b0 1
02
b0 3
b0 4
b0 5
b0 6
b0 7
b0 8
b1 9
b0 I
b0 J
b0 L
#10000
0!
0*
#15000
1!
1*
#16000
0"
0+
#20000
0!
0*
#25000
1!
b1 '
1*
1,
b1 /
b10000000100000001000000010000 0
12
b0 3
b0 4
b1 5
b10000000100000001000000010000 6
b0 7
b1 8
b10 9
#30000
0!
0*
#35000
1!
b10 '
1*
b10 /
b1000000010000000100000001 0
12
b0 3
b0 4
b10 5
b1000000010000000100000001 6
b0 7
b10 8
b11 9
b0 I
b0 J
#40000
0!
0*
#45000
1!
b11 '
1*
b11 /
b101 0
12
b0 3
b0 4
b11 5
b101 6
b0 7
b11 8
b100 9
b0 I
b0 J
#50000
0!
0*
#55000
1!
b10000000100000001000000010000 #
b1000000010000000100000001 $
b10001000100010001000100010001 %
0&
b100 '
1*
b1 -
b10 .
b100 /
b10001000100010001000100010001 0
12
b1 3
b10 4
b100 5
b10001000100010001000100010001 6
b0 7
b100 8
b101 9
b10000000100000001000000010000 I
b1000000010000000100000001 J
b10001000100010001000100010001 L
#60000
0!
0*
#65000
1!
b1111000011110000111100001111 %
0&
b101 '
1*
b1 -
b10 .
b101 /
b1111000011110000111100001111 0
b1 1
12
b1 3
b10 4
b101 5
b1111000011110000111100001111 6
b1 7
b101 8
b110 9
b10000000100000001000000010000 I
b1000000010000000100000001 J
b1111000011110000111100001111 L
#70000
0!
0*
#75000
1!
b0 %
1&
b110 '
1*
b1 -
b10 .
b110 /
b0 0
b10 1
12
b1 3
b10 4
b110 5
b0 6
b10 7
b110 8
b111 9
b10000000100000001000000010000 I
b1000000010000000100000001 J
b0 L
#80000
0!
0*
#85000
1!
b10001000100010001000100010001 %
0&
b111 '
1*
b1 -
b10 .
b111 /
b10001000100010001000100010001 0
b11 1
12
b1 3
b10 4
b111 5
b10001000100010001000100010001 6
b11 7
b111 8
b1000 9
b10001000100010001000100010001 L
#90000
0!
0*
#95000
1!
b1000 '
1*
b1 -
b10 .
b1000 /
b100 1
12
b1 3
b10 4
b1000 5
b10001000100010001000100010001 6
b100 7
b1000 8
b1001 9
b10000000100000001000000010000 I
b1000000010000000100000001 J
b10001000100010001000100010001 L
#100000
0!
0*
#105000
1!
b101 $
b10000000100000001000000000 %
0&
b1001 '
1*
b1 -
b11 .
b1001 /
b10000000100000001000000000 0
b101 1
12
b1 3
b11 4
b1001 5
b10000000100000001000000000 6
b101 7
b1001 8
b1010 9
b10000000100000001000000010000 I
b101 J
b10000000100000001000000000 L
#110000
0!
0*
#115000
1!
b100000001000000010000000 %
0&
b1010 '
1*
b1 -
b11 .
b1010 /
b100000001000000010000000 0
b110 1
12
b1 3
b11 4
b1010 5
b100000001000000010000000 6
b110 7
b1010 8
b1011 9
b10000000100000001000000010000 I
b101 J
b100000001000000010000000 L
#120000
0!
0*
#125000
1!
b10000000100000001000000010000 $
b0 %
1&
b1011 '
1*
b1 -
b1 .
b1011 /
b1 0
b111 1
12
b1 3
b1 4
b1011 5
b1 6
b111 7
b1011 8
b1100 9
b10000000100000001000000010000 I
b10000000100000001000000010000 J
b0 L
#130000
0!
0*
#135000
1!
b0 #
b0 $
b0 %
1&
b1100 '
1*
b0 -
b0 .
b1100 /
b10101011110011011010101111001101 0
b0 1
12
b0 3
b0 4
b1100 5
b10101011110011011010101111001101 6
b0 7
b1100 8
b1101 9
b0 I
b0 J
b0 L
#140000
0!
0*
#145000
1!
b10101011110011011010101111001101 #
b10101011110011011010101111001101 %
0&
b1101 '
1*
0,
b1100 -
b0 /
b0 0
02
b1100 3
b0 4
b0 5
b0 6
b0 7
b1101 8
b1110 9
b10101011110011011010101111001101 I
b0 J
b10101011110011011010101111001101 L
#150000
0!
0*
#155000
1!
b0 #
b0 %
1&
b1110 '
1*
b0 -
02
b0 3
b0 4
b0 5
b0 6
b0 7
b1110 8
b0 I
b0 L
#160000
0!
0*
#165000
1!
1*
#170000
0!
0*
#175000
1!
1*
#176000
b10001000100010001000100010001 #
b10001000100010001000100010001 %
0&
b100 -
02
b0 3
b0 4
b0 5
b0 6
b0 7
b10001000100010001000100010001 I
b10001000100010001000100010001 L
#177000
b1111000011110000111100001111 #
b1111000011110000111100001111 %
0&
b1 (
b101 -
02
b0 3
b0 4
b0 5
b0 6
b0 7
b1111000011110000111100001111 I
b1111000011110000111100001111 L
#178000
b0 #
b0 %
1&
b10 (
b110 -
02
b0 3
b0 4
b0 5
b0 6
b0 7
b0 I
b0 L
#179000
b10001000100010001000100010001 #
b10001000100010001000100010001 %
0&
b11 (
b111 -
02
b0 3
b0 4
b0 5
b0 6
b0 7
b10001000100010001000100010001 I
b10001000100010001000100010001 L
#180000
0!
b100 (
0*
b1000 -
b10001000100010001000100010001 I
#181000
b10000000100000001000000000 #
b10000000100000001000000000 %
0&
b101 (
b1001 -
02
b0 3
b0 4
b0 5
b0 6
b0 7
b10000000100000001000000000 I
b10000000100000001000000000 L
#182000
b100000001000000010000000 #
b100000001000000010000000 %
0&
b110 (
b1010 -
02
b0 3
b0 4
b0 5
b0 6
b0 7
b100000001000000010000000 I
b100000001000000010000000 L
#183000
b1 #
b1 %
0&
b111 (
b1011 -
02
b0 3
b0 4
b0 5
b0 6
b0 7
b1 I
b1 L
#184000
b10101011110011011010101111001101 #
b10101011110011011010101111001101 %
0&
b1000 (
b1100 -
02
b0 3
b0 4
b0 5
b0 6
b0 7
b10101011110011011010101111001101 I
b10101011110011011010101111001101 L
#185000
1!
b0 #
b0 %
1&
b1001 (
1*
b0 -
02
b0 3
b0 4
b0 5
b0 6
b0 7
b0 I
b0 L
#186000
b1010 (
b0 -
